qt_tree/__init__.py
qt_tree/default_config.json
qt_tree/node.py
qt_tree/scene.py
qt_tree/slot.py
qt_tree/util.py
qt_tree/view.py
qt_tree-0.1.2.dist-info/LICENSE
qt_tree-0.1.2.dist-info/METADATA
qt_tree-0.1.2.dist-info/WHEEL
qt_tree-0.1.2.dist-info/top_level.txt
qt_tree-0.1.2.dist-info/RECORD
