Metadata-Version: 2.1
Name: qt-tree
Version: 0.1.2
Summary: Graphical user interface for editing and visualizing tree data structure
Home-page: https://github.com/ktrk115/qt-tree
Author: Kotaro Kikuchi
Author-email: ktrk115@gmail.com
License: UNKNOWN
Keywords: Qt,tree structure,tree editor
Platform: UNKNOWN
Classifier: Programming Language :: Python :: 3
Classifier: License :: OSI Approved :: MIT License
Classifier: Operating System :: OS Independent
Requires-Dist: PySide2
Requires-Dist: anytree
Provides-Extra: pillow
Requires-Dist: pillow ; extra == 'pillow'
